LICENSE
beautysh/beautysh.py
beautysh-6.2.0.dist-info/entry_points.txt
beautysh-6.2.0.dist-info/LICENSE
beautysh-6.2.0.dist-info/WHEEL
beautysh-6.2.0.dist-info/METADATA
beautysh-6.2.0.dist-info/RECORD
