Metadata-Version: 2.1
Name: beautysh
Version: 6.2.0
Summary: A Bash beautifier for the masses.
Home-page: https://github.com/lovesegfault/beautysh
License: MIT
Keywords: beautify,bash,shell,beautifier,script,auto
Author: Bernardo Meurer
Author-email: bernardo@meurer.org
Requires-Python: >=3.6.2,<4.0.0
Classifier: Development Status :: 5 - Production/Stable
Classifier: Environment :: Console
Classifier: Intended Audience :: Developers
Classifier: License :: OSI Approved :: MIT License
Classifier: Operating System :: OS Independent
Classifier: Programming Language :: Python :: 3
Classifier: Programming Language :: Python :: 3 :: Only
Classifier: Programming Language :: Python :: 3.7
Classifier: Programming Language :: Python :: 3.8
Classifier: Programming Language :: Python :: 3.9
Classifier: Topic :: Software Development :: Libraries :: Python Modules
Classifier: Topic :: Software Development :: Quality Assurance
Classifier: Topic :: Text Processing :: Filters
Classifier: Topic :: Utilities
Requires-Dist: colorama (>=0.4.4,<0.5.0)
Requires-Dist: types-colorama (>=0.4.3,<0.5.0)
Requires-Dist: types-setuptools (>=57.4.0,<58.0.0)
Project-URL: Repository, https://github.com/lovesegfault/beautysh
